Workbook
Name Slicer_segment: #N/A
Name Slicer_speedometer_type: #N/A

Sheet Executive_Dashboard
B2: ENTERPRISE EXECUTIVE ANALYTICS SUITE | AUTONOMOUS DATA PROFILER | REAL-TIME SLICER ENGINE
B3: EXECUTIVE PERFORMANCE & MULTI-VARIABLE PREDICTIVE DASHBOARD
B6: FILTERED VOLUME | D6: TOTAL GST_AMOUNT_I | F6: AVERAGE GST_AMOUNT_I | H6: TOTAL FACTORY_PRIC | J6: DISPERSION (STD DEV) | L6: PEAK OBSERVATION | N6: BASELINE FLOOR | P6: OPERATING MARGIN
B7: =Pivot_Calculations!D4 -> 1000 | D7: =Pivot_Calculations!A4 -> 39293438 | F7: =Pivot_Calculations!B4 -> 39293.438 | H7: =Pivot_Calculations!E4 -> 136817562 | J7: =Pivot_Calculations!C4 -> 21794.3 | L7: =Pivot_Calculations!F4 -> 146244 | N7: =Pivot_Calculations!G4 -> 12031 | P7: =IF(Pivot_Calculations!A4>0, Pivot_Calculations!E4/Pivot_Calculations!A4, 0) -> 3.4819443
B8: 100% Ingested Samples | D8: Real-Time Net Aggregate | F8: Mean Velocity | H8: Secondary Net Pool | J8: Gaussian Sigma Width | L8: Maximum Recorded Value | N8: Minimum Recorded Value | P8: Efficiency Ratio
B10: STATISTICAL MODELING FINDINGS & STRATEGIC DIRECTIVES:_x000D_ * Model Fit: Stochastic / Multi-Factor Variance (R^2 = 0.003) with [+] Upward Velocity._x000D_ * OLS Slope: m = +4.3928 per period; Next 1-Step Projected Baseline = 41,492.02._x000D_ * Anomaly Diagnostic: 48 observations (4.8%) exceed Tukey's 1.5xIQR envelope [-13,671.5 to 83,452.5]._x000D_ * Pareto Concentration: Top 25% transactions contribute 44.5% of aggregate GST_AMOUNT_I._x000D_ _x000D_ ACTIONABLE STRATEGIC RECOMMENDATIONS:_x000D_ >> Allocate operational resources aligned to projected baseline target (41,492)._x000D_ >> Use interactive Slicers on the right to isolate and remediate localized segment anomalies. | J10: PREDICTIVE MODELING & OLS REGRESSION SPECIFICATION
J11: Target Variable (Y) | M11: gst_amount_inr
J12: Algorithm Architecture | M12: Ordinary Least Squares (OLS) Linear
J13: Slope Coefficient (m) | M13: 4.3928
J14: Y-Intercept (b) | M14: 37094.86
J15: Goodness-of-Fit (R^2) | M15: 0.0034
J16: Standard Error (S_e) | M16: 21768.24

Sheet Pivot_Calculations
AA1: Statistic | AB1: Result | AD1: X_Idx | AE1: Y_Val
AA2: Total_Rows | AB2: =COUNTA(Raw_Data!A2:A1001) -> 1000 | AD2: 1 | AE2: =Raw_Data!L2 -> 28219
A3: Sum_Primary | B3: Avg_Primary | C3: StdDev_Primary | D3: Count_Recs | E3: Sum_Secondary | F3: Max_Primary | G3: Min_Primary | I3: Row Labels | J3: Trend_gst_amou | M3: Row Labels | N3: Ranked_gst_amou | Q3: Row Labels | R3: Share_gst_amou | U3: Row Labels | V3: Primary_gst_amou | W3: Secondary_factory_ | AA3: Sum_Num1 | AB3: =SUM(Raw_Data!L2:L1001) -> 39293438 | AD3: 2 | AE3: =Raw_Data!L3 -> 34562
A4: 39293438 | B4: 39293.438 | C4: 21794.3 | D4: 1000 | E4: 136817562 | F4: 146244 | G4: 12031 | I4: 2020 | J4: 6055238 | M4: budget | N4: 4652150 | Q4: Analog | R4: 4391643 | U4: budget | V4: 4652150 | W4: 16614850 | AA4: Avg_Num1 | AB4: =AVERAGE(Raw_Data!L2:L1001) -> 39293.438 | AD4: 3 | AE4: =Raw_Data!L4 -> 16844
I5: 2021 | J5: 6482591 | M5: mid | N5: 13802031 | Q5: Digital | R5: 27161075 | U5: mid | V5: 13802031 | W5: 49292969 | AA5: Std_Num1 | AB5: =_xlfn.STDEV.S(Raw_Data!L2:L1001) -> 21794.3 | AD5: 4 | AE5: =Raw_Data!L5 -> 41125
I6: 2022 | J6: 6546525 | M6: premium | N6: 20839257 | Q6: Semi-Digital | R6: 7740720 | U6: premium | V6: 20839257 | W6: 70909743 | AA6: Med_Num1 | AB6: =MEDIAN(Raw_Data!L2:L1001) -> 34671.5 | AD6: 5 | AE6: =Raw_Data!L6 -> 51588
I7: 2023 | J7: 6221006 | M7: Grand Total | N7: 39293438 | Q7: Grand Total | R7: 39293438 | U7: Grand Total | V7: 39293438 | W7: 136817562 | AA7: Q1_Num1 | AB7: =_xlfn.PERCENTILE.INC(Raw_Data!L2:L1001, 0.25) -> 22750 | AD7: 6 | AE7: =Raw_Data!L7 -> 48038
I8: 2024 | J8: 7241686 | AA8: Q3_Num1 | AB8: =_xlfn.PERCENTILE.INC(Raw_Data!L2:L1001, 0.75) -> 47031 | AD8: 7 | AE8: =Raw_Data!L8 -> 17062
I9: 2025 | J9: 6746392 | AD9: 8 | AE9: =Raw_Data!L9 -> 20562
I10: Grand Total | J10: 39293438 | AA10: Slope_m | AB10: =SLOPE(AE2:AE1001, AD2:AD1001) -> 4.3927702 | AD10: 9 | AE10: =Raw_Data!L10 -> 26906
AA11: Intercept_b | AB11: =INTERCEPT(AE2:AE1001, AD2:AD1001) -> 37094.857 | AD11: 10 | AE11: =Raw_Data!L11 -> 45938
AA12: RSQ_Score | AB12: =RSQ(AE2:AE1001, AD2:AD1001) -> 0.0033887845 | AD12: 11 | AE12: =Raw_Data!L12 -> 29750
AA13: Steyx_Se | AB13: =STEYX(AE2:AE1001, AD2:AD1001) -> 21768.238 | AD13: 12 | AE13: =Raw_Data!L13 -> 33906
AA14: Forecast_Next | AB14: =AB10*1001+AB11 -> 41492.019 | AD14: 13 | AE14: =Raw_Data!L14 -> 64531
AD15: 14 | AE15: =Raw_Data!L15 -> 16406
AD16: 15 | AE16: =Raw_Data!L16 -> 36531
AD17: 16 | AE17: =Raw_Data!L17 -> 38500
AD18: 17 | AE18: =Raw_Data!L18 -> 17062
AD19: 18 | AE19: =Raw_Data!L19 -> 20781
AD20: 19 | AE20: =Raw_Data!L20 -> 48781
AD21: 20 | AE21: =Raw_Data!L21 -> 45281
AD22: 21 | AE22: =Raw_Data!L22 -> 52771
AD23: 22 | AE23: =Raw_Data!L23 -> 39156
AD24: 23 | AE24: =Raw_Data!L24 -> 49438
AD25: 24 | AE25: =Raw_Data!L25 -> 37188
AD26: 25 | AE26: =Raw_Data!L26 -> 41125
... AD1001: 1000 | AE1001: =Raw_Data!L1001 -> 45938

Sheet Raw_Data
A1: brand | B1: model | C1: cc | D1: segment | E1: year | F1: speedometer_type | G1: top_speed_kmh | H1: mileage_kmpl | I1: fuel_tank_liters | J1: factory_price_inr | K1: gst_rate_pct | L1: gst_amount_inr | M1: ex_showroom_inr | N1: on_road_price_inr | O1: overall_score | P1: price_increase_scenario_pct | Q1: buyer_behaviour | R1: price_sensitivity
A2: Honda | B2: Hornet 2.0 | C2: 184 | D2: mid | E2: 2020 | F2: Digital | G2: 137 | H2: 43.8 | I2: 10.1 | J2: 100781 | K2: 28 | L2: 28219 | M2: 129000 | N2: 147604 | O2: 70 | P2: 9.3 | Q2: Will likely switch brand | R2: High
A3: Bajaj | B3: Pulsar N250 | C3: 249 | D3: mid | E3: 2024 | F3: Digital | G3: 157 | H3: 33.2 | I3: 14.9 | J3: 123438 | K3: 28 | L3: 34562 | M3: 158000 | N3: 185890 | O3: 71 | P3: 4.1 | Q3: Might reconsider | R3: Medium
A4: Hero | B4: Splendor Plus | C4: 97 | D4: budget | E4: 2020 | F4: Analog | G4: 95 | H4: 64.2 | I4: 8.7 | J4: 60156 | K4: 28 | L4: 16844 | M4: 77000 | N4: 89751 | O4: 57 | P4: 2.3 | Q4: Might reconsider | R4: Medium
A5: Royal Enfield | B5: Thunderbird 350X | C5: 346 | D5: premium | E5: 2025 | F5: Semi-Digital | G5: 152 | H5: 29.1 | I5: 17.3 | J5: 146875 | K5: 28 | L5: 41125 | M5: 188000 | N5: 221689 | O5: 67 | P5: 8.7 | Q5: Will likely switch brand | R5: High
A6: Royal Enfield | B6: Scram 411 | C6: 411 | D6: premium | E6: 2023 | F6: Semi-Digital | G6: 165 | H6: 23.4 | I6: 14.9 | J6: 166412 | K6: 31 | L6: 51588 | M6: 218000 | N6: 251257 | O6: 73 | P6: 13.1 | Q6: Will definitely switch | R6: Very High
A7: Royal Enfield | B7: Scram 411 | C7: 411 | D7: premium | E7: 2021 | F7: Semi-Digital | G7: 201 | H7: 24.3 | I7: 16.7 | J7: 154962 | K7: 31 | L7: 48038 | M7: 203000 | N7: 235810 | O7: 71 | P7: 9.5 | Q7: Will likely switch brand | R7: High
A8: TVS | B8: Star City Plus | C8: 109 | D8: budget | E8: 2020 | F8: Semi-Digital | G8: 92 | H8: 73.2 | I8: 8.5 | J8: 60938 | K8: 28 | L8: 17062 | M8: 78000 | N8: 93929 | O8: 71 | P8: 5.5 | Q8: Will likely switch brand | R8: High
A9: Hero | B9: Super Splendor | C9: 125 | D9: budget | E9: 2023 | F9: Semi-Digital | G9: 115 | H9: 60 | I9: 13.5 | J9: 73438 | K9: 28 | L9: 20562 | M9: 94000 | N9: 110296 | O9: 66 | P9: 10.2 | Q9: Will definitely switch | R9: Very High
A10: Yamaha | B10: FZ-S V3 | C10: 149 | D10: mid | E10: 2021 | F10: Semi-Digital | G10: 118 | H10: 51.9 | I10: 14 | J10: 96094 | K10: 28 | L10: 26906 | M10: 123000 | N10: 143257 | O10: 71 | P10: 6.6 | Q10: Will likely switch brand | R10: High
A11: Honda | B11: CB350 H'ness | C11: 348 | D11: premium | E11: 2020 | F11: Digital | G11: 145 | H11: 29.3 | I11: 15.7 | J11: 164062 | K11: 28 | L11: 45938 | M11: 210000 | N11: 236511 | O11: 82 | P11: 6.9 | Q11: Will likely switch brand | R11: High
A12: Yamaha | B12: FZ-X | C12: 149 | D12: mid | E12: 2022 | F12: Digital | G12: 108 | H12: 57.4 | I12: 13.1 | J12: 106250 | K12: 28 | L12: 29750 | M12: 136000 | N12: 160631 | O12: 79 | P12: 13.4 | Q12: Will definitely switch | R12: Very High
A13: Royal Enfield | B13: Hunter 350 | C13: 349 | D13: premium | E13: 2024 | F13: Semi-Digital | G13: 148 | H13: 34.9 | I13: 19.4 | J13: 121094 | K13: 28 | L13: 33906 | M13: 155000 | N13: 181109 | O13: 74 | P13: 11.7 | Q13: Will definitely switch | R13: Very High
... A1001: Royal Enfield | B1001: Meteor 350 | C1001: 349 | D1001: premium | E1001: 2024 | F1001: Semi-Digital | G1001: 153 | H1001: 31.4 | I1001: 13.2 | J1001: 164062 | K1001: 28 | L1001: 45938 | M1001: 210000 | N1001: 243807 | O1001: 72 | P1001: 7.5 | Q1001: Will likely switch brand | R1001: High

Sheet Sheet1
